[
  {
    "description": "    Complete Questionnaire to create acquisition",
    "keyword": "Feature",
    "name": "Complete Questionnaire to create acquisition",
    "line": 1,
    "id": "complete-questionnaire-to-create-acquisition",
    "tags": [],
    "uri": "e2e\\features\\3questions.feature",
    "elements": [
      {
        "id": "complete-questionnaire-to-create-acquisition;create-product-based-new-requirement-acq",
        "keyword": "Scenario",
        "line": 4,
        "name": "Create Product Based New requirement Acq",
        "tags": [],
        "type": "scenario",
        "steps": [
          {
            "keyword": "Before",
            "hidden": true,
            "match": {
              "location": "e2e\\steps\\1cert\\1cert.steps.ts:7"
            },
            "result": {
              "status": "passed"
            }
          },
          {
            "keyword": "Before",
            "hidden": true,
            "match": {
              "location": "e2e\\steps\\2login\\2login.steps.ts:8"
            },
            "result": {
              "status": "passed"
            }
          },
          {
            "keyword": "Before",
            "hidden": true,
            "match": {
              "location": "e2e\\steps\\3questions\\3questions.steps.ts:7"
            },
            "result": {
              "status": "passed"
            }
          },
          {
            "keyword": "Before",
            "hidden": true,
            "match": {
              "location": "e2e\\steps\\4general\\4general.steps.ts:7"
            },
            "result": {
              "status": "passed"
            }
          },
          {
            "keyword": "Before",
            "hidden": true,
            "match": {
              "location": "e2e\\steps\\5sow\\5sow.steps.ts:7"
            },
            "result": {
              "status": "passed"
            }
          },
          {
            "keyword": "Before",
            "hidden": true,
            "match": {
              "location": "e2e\\steps\\7security\\7security.steps.ts:7"
            },
            "result": {
              "status": "passed"
            }
          },
          {
            "keyword": "Before",
            "hidden": true,
            "match": {
              "location": "e2e\\steps\\7OtherConsiderations\\7OtherConsiderations.steps.ts:7"
            },
            "result": {
              "status": "passed"
            }
          },
          {
            "keyword": "Before",
            "hidden": true,
            "match": {
              "location": "e2e\\steps\\8eval\\8eval.steps.ts:8"
            },
            "result": {
              "status": "passed"
            }
          },
          {
            "keyword": "Before",
            "hidden": true,
            "match": {
              "location": "e2e\\steps\\9poc\\9poc.steps.ts:7"
            },
            "result": {
              "status": "passed"
            }
          },
          {
            "keyword": "Before",
            "hidden": true,
            "match": {
              "location": "e2e\\steps\\e-draftingSolicitation\\e-draftingSolicitation.steps.ts:7"
            },
            "result": {
              "status": "passed"
            }
          },
          {
            "keyword": "Before",
            "hidden": true,
            "match": {
              "location": "e2e\\steps\\f-formsf1449\\f-formsf1449.steps.ts:7"
            },
            "result": {
              "status": "passed"
            }
          },
          {
            "keyword": "Before",
            "hidden": true,
            "match": {
              "location": "e2e\\steps\\g-publishSolicitation\\g-publishSolicitation.steps.ts:7"
            },
            "result": {
              "status": "passed"
            }
          },
          {
            "keyword": "Before",
            "hidden": true,
            "match": {
              "location": "e2e\\steps\\h-createAmendment\\h-createAmendment.steps.ts:7"
            },
            "result": {
              "status": "passed",
              "duration": 1000000
            }
          },
          {
            "keyword": "Before",
            "hidden": true,
            "match": {
              "location": "e2e\\steps\\i-formsf30\\i-formsf30.steps.ts:7"
            },
            "result": {
              "status": "passed"
            }
          },
          {
            "keyword": "Before",
            "hidden": true,
            "match": {
              "location": "e2e\\steps\\j-soc\\j-soc.steps.ts:7"
            },
            "result": {
              "status": "passed"
            }
          },
          {
            "arguments": [],
            "keyword": "Given ",
            "line": 5,
            "name": "User on program manager dashboard",
            "match": {
              "location": "e2e\\steps\\3questions\\3questions.steps.ts:9"
            },
            "result": {
              "status": "passed",
              "duration": 502000000
            }
          },
          {
            "arguments": [],
            "keyword": "When ",
            "line": 6,
            "name": "User clicks on create new",
            "match": {
              "location": "e2e\\steps\\3questions\\3questions.steps.ts:13"
            },
            "result": {
              "status": "passed",
              "duration": 1109000000
            }
          },
          {
            "arguments": [],
            "keyword": "And ",
            "line": 7,
            "name": "User selects create new requirement and clicks next",
            "match": {
              "location": "e2e\\steps\\3questions\\3questions.steps.ts:18"
            },
            "result": {
              "status": "passed",
              "duration": 3115000000
            }
          },
          {
            "arguments": [],
            "keyword": "And ",
            "line": 8,
            "name": "User selects Products or Services and clicks next",
            "match": {
              "location": "e2e\\steps\\3questions\\3questions.steps.ts:25"
            },
            "result": {
              "status": "passed",
              "duration": 4813000000
            }
          },
          {
            "arguments": [],
            "keyword": "And ",
            "line": 9,
            "name": "User selects category of contracting and clicks next",
            "match": {
              "location": "e2e\\steps\\3questions\\3questions.steps.ts:35"
            },
            "result": {
              "status": "passed",
              "duration": 4773000000
            }
          },
          {
            "arguments": [],
            "keyword": "And ",
            "line": 10,
            "name": "User selects products and service PSC Considerations and clicks next",
            "match": {
              "location": "e2e\\steps\\3questions\\3questions.steps.ts:47"
            },
            "result": {
              "status": "passed",
              "duration": 4698000000
            }
          },
          {
            "arguments": [],
            "keyword": "And ",
            "line": 11,
            "name": "User types keywords or phrases and clicks next",
            "match": {
              "location": "e2e\\steps\\3questions\\3questions.steps.ts:57"
            },
            "result": {
              "status": "passed",
              "duration": 3162000000
            }
          },
          {
            "arguments": [],
            "keyword": "And ",
            "line": 12,
            "name": "User selects anticipated award date and clicks next",
            "match": {
              "location": "e2e\\steps\\3questions\\3questions.steps.ts:65"
            },
            "result": {
              "status": "passed",
              "duration": 3191000000
            }
          },
          {
            "arguments": [],
            "keyword": "And ",
            "line": 13,
            "name": "User selects no for unusual and compelling urgency and clicks next",
            "match": {
              "location": "e2e\\steps\\3questions\\3questions.steps.ts:73"
            },
            "result": {
              "status": "passed",
              "duration": 3110000000
            }
          },
          {
            "arguments": [],
            "keyword": "And ",
            "line": 14,
            "name": "User enters estimated budget and clicks next",
            "match": {
              "location": "e2e\\steps\\3questions\\3questions.steps.ts:80"
            },
            "result": {
              "status": "passed",
              "duration": 3203000000
            }
          },
          {
            "arguments": [],
            "keyword": "And ",
            "line": 15,
            "name": "User enters project title and clicks submit",
            "match": {
              "location": "e2e\\steps\\3questions\\3questions.steps.ts:88"
            },
            "result": {
              "status": "passed",
              "duration": 3611000000
            }
          },
          {
            "arguments": [],
            "keyword": "Then ",
            "line": 16,
            "name": "User should see options like “General”, “Statement of Work”, “Market Research”, “Funding”, “Evaluations”, “Security”, “Other Considerations”, “Attachments”, “Points of Contact”, “Resources” on the left nav",
            "match": {
              "location": "e2e\\steps\\3questions\\3questions.steps.ts:95"
            },
            "result": {
              "status": "passed",
              "duration": 8001000000
            }
          },
          {
            "keyword": "After",
            "hidden": true,
            "match": {
              "location": "node_modules\\protractor-cucumber-framework\\lib\\resultsCapturer.js:26"
            },
            "result": {
              "status": "passed"
            }
          }
        ]
      }
    ],
    "metadata": {
      "browser": {
        "name": "chrome",
        "version": "87.0.4280.66"
      },
      "device": "",
      "platform": {
        "name": "",
        "version": ""
      }
    }
  }
]
